{
	"definitions" : [
		{
			"name" : "Camel Main 4.17.0",
			"version" : "4.17.0",
			"runtime" : "Main",
			"fileName" : "camel-main/4.17.0/index-6ca1a564c887fdc97f31bf287139fe98.json"
		},
		{
			"name" : "Camel Main 4.14.4",
			"version" : "4.14.4",
			"runtime" : "Main",
			"fileName" : "camel-main/4.14.4/index-e39740086f05ec34587ec987c48d5e7f.json"
		},
		{
			"name" : "Camel Main 4.14.2.redhat-00011",
			"version" : "4.14.2.redhat-00011",
			"runtime" : "Main",
			"fileName" : "camel-main/4.14.2.redhat-00011/index-b306ecee84c5d1ba8bd25a56a319b3c1.json"
		},
		{
			"name" : "Camel Main 4.10.7.redhat-00009",
			"version" : "4.10.7.redhat-00009",
			"runtime" : "Main",
			"fileName" : "camel-main/4.10.7.redhat-00009/index-964a99365552176879ad4e8e713145d7.json"
		},
		{
			"name" : "Camel Main 4.8.5.redhat-00008",
			"version" : "4.8.5.redhat-00008",
			"runtime" : "Main",
			"fileName" : "camel-main/4.8.5.redhat-00008/index-34a81e5082764aeff2ddb56872b1be6f.json"
		},
		{
			"name" : "Camel Main 4.4.0.redhat-00046",
			"version" : "4.4.0.redhat-00046",
			"runtime" : "Main",
			"fileName" : "camel-main/4.4.0.redhat-00046/index-d6d4118d6c1019c5fc37e85b2a47935e.json"
		},
		{
			"name" : "Camel Quarkus 3.30.0",
			"version" : "3.30.0",
			"runtime" : "Quarkus",
			"fileName" : "camel-quarkus/3.30.0/index-31de796dfb0b0fb5e473ee562d5acfa9.json"
		},
		{
			"name" : "Camel Quarkus 3.27.2",
			"version" : "3.27.2",
			"runtime" : "Quarkus",
			"fileName" : "camel-quarkus/3.27.2/index-6fd09e9633aa500e16d66fe53df85626.json"
		},
		{
			"name" : "Camel Quarkus 3.27.1.redhat-00003",
			"version" : "3.27.1.redhat-00003",
			"runtime" : "Quarkus",
			"fileName" : "camel-quarkus/3.27.1.redhat-00003/index-a36fd293077af59a5804044271ca5b9c.json"
		},
		{
			"name" : "Camel Quarkus 3.20.0.redhat-00010",
			"version" : "3.20.0.redhat-00010",
			"runtime" : "Quarkus",
			"fileName" : "camel-quarkus/3.20.0.redhat-00010/index-a8130b61d36b799bed73e482f6257582.json"
		},
		{
			"name" : "Camel Quarkus 3.15.0.redhat-00010",
			"version" : "3.15.0.redhat-00010",
			"runtime" : "Quarkus",
			"fileName" : "camel-quarkus/3.15.0.redhat-00010/index-7726079e72f3e510935266730d9e5c5b.json"
		},
		{
			"name" : "Camel Quarkus 3.8.0.redhat-00018",
			"version" : "3.8.0.redhat-00018",
			"runtime" : "Quarkus",
			"fileName" : "camel-quarkus/3.8.0.redhat-00018/index-63c5b7400780cc24c557780094ce0466.json"
		},
		{
			"name" : "Camel Spring Boot 4.17.0",
			"version" : "4.17.0",
			"runtime" : "Spring Boot",
			"fileName" : "camel-springboot/4.17.0/index-5a71caeb98fbc60139afac7f1474f365.json"
		},
		{
			"name" : "Camel Spring Boot 4.14.4",
			"version" : "4.14.4",
			"runtime" : "Spring Boot",
			"fileName" : "camel-springboot/4.14.4/index-c5a062ae7d6562c30a66b7c197990dbf.json"
		},
		{
			"name" : "Camel Spring Boot 4.14.2.redhat-00015",
			"version" : "4.14.2.redhat-00015",
			"runtime" : "Spring Boot",
			"fileName" : "camel-springboot/4.14.2.redhat-00015/index-987de0450d49ef49cf6fdaf5679fd013.json"
		},
		{
			"name" : "Camel Spring Boot 4.10.7.redhat-00013",
			"version" : "4.10.7.redhat-00013",
			"runtime" : "Spring Boot",
			"fileName" : "camel-springboot/4.10.7.redhat-00013/index-77047df70d0e17ffea2159607d220302.json"
		},
		{
			"name" : "Camel Spring Boot 4.8.5.redhat-00008",
			"version" : "4.8.5.redhat-00008",
			"runtime" : "Spring Boot",
			"fileName" : "camel-springboot/4.8.5.redhat-00008/index-511baa268daedc672cb34115be6d2e1.json"
		},
		{
			"name" : "Camel Spring Boot 4.4.0.redhat-00039",
			"version" : "4.4.0.redhat-00039",
			"runtime" : "Spring Boot",
			"fileName" : "camel-springboot/4.4.0.redhat-00039/index-e932d8bf76abf66231f19a2122a8477f.json"
		},
		{
			"name" : "Citrus 4.9.2",
			"version" : "4.9.2",
			"runtime" : "Citrus",
			"fileName" : "citrus/4.9.2/index.json"
		}
	],
	"version" : 3,
	"name" : "Default Kaoto catalog"
}